thermo/__init__.py
thermo/activity.py
thermo/base.py
thermo/bulk.py
thermo/chemical.py
thermo/chemical_package.py
thermo/chemical_utils.py
thermo/coolprop.py
thermo/database.py
thermo/datasheet.py
thermo/electrochem.py
thermo/eos.py
thermo/eos_alpha_functions.py
thermo/eos_mix.py
thermo/eos_mix_methods.py
thermo/eos_volume.py
thermo/equilibrium.py
thermo/fitting.py
thermo/functional_groups.py
thermo/heat_capacity.py
thermo/interaction_parameters.py
thermo/interface.py
thermo/law.py
thermo/mixture.py
thermo/nrtl.py
thermo/numba.py
thermo/permittivity.py
thermo/phase_change.py
thermo/phase_identification.py
thermo/property_package.py
thermo/redlich_kister.py
thermo/regular_solution.py
thermo/serialize.py
thermo/stream.py
thermo/test_utils.py
thermo/thermal_conductivity.py
thermo/unifac.py
thermo/uniquac.py
thermo/units.py
thermo/vapor_pressure.py
thermo/vectorized.py
thermo/viscosity.py
thermo/volume.py
thermo/wilson.py
thermo/Interaction Parameters/PRTranslated_best_henry_T_dep.json
thermo/Interaction Parameters/Sander_henry_T_dep.json
thermo/Interaction Parameters/Sander_henry_const.json
thermo/Interaction Parameters/eppr78_common.json
thermo/Interaction Parameters/ChemSep/Artistic_license_2_0.txt
thermo/Interaction Parameters/ChemSep/henry.json
thermo/Interaction Parameters/ChemSep/nrtl.ipd
thermo/Interaction Parameters/ChemSep/nrtl.json
thermo/Interaction Parameters/ChemSep/pr.ipd
thermo/Interaction Parameters/ChemSep/pr.json
thermo/Interaction Parameters/ChemSep/uniquac.json
thermo/Interaction Parameters/ChemSep/wilson.json
thermo/Law/Canada Feb 11 2015 - DSL.csv.gz
thermo/Law/EC Inventory No Longer Polymers (NLP).csv
thermo/Law/ECHA Tonnage Bands.csv.zip
thermo/Law/EINECS 2015-03.csv.gz
thermo/Law/EPA 2012 Chemical Data Reporting.csv
thermo/Law/EPA Chemical Data Reporting - 2012.csv.gz
thermo/Law/HPV 2015 March 3.csv
thermo/Law/SPIN Inventory 2015-03.csv.gz
thermo/Law/TSCA Inventory 2016-01.csv.gz
thermo/Misc/Ho_1972_thermal_conductivity_solid.json
thermo-0.5.0.dist-info/licenses/AUTHORS
thermo-0.5.0.dist-info/licenses/LICENSE.txt
thermo-0.5.0.dist-info/METADATA
thermo-0.5.0.dist-info/WHEEL
thermo-0.5.0.dist-info/top_level.txt
thermo-0.5.0.dist-info/RECORD
